odoo/addons/l10n_es_vat_book_igic/README.rst
odoo/addons/l10n_es_vat_book_igic/__init__.py
odoo/addons/l10n_es_vat_book_igic/__manifest__.py
odoo/addons/l10n_es_vat_book_igic/data/aeat.vat.book.map.line.csv
odoo/addons/l10n_es_vat_book_igic/data/l10n.es.aeat.map.tax.line.account.csv
odoo/addons/l10n_es_vat_book_igic/data/l10n.es.aeat.map.tax.line.tax.csv
odoo/addons/l10n_es_vat_book_igic/i18n/l10n_es_vat_book_igic.pot
odoo/addons/l10n_es_vat_book_igic/readme/CONFIGURE.md
odoo/addons/l10n_es_vat_book_igic/readme/CONTRIBUTORS.md
odoo/addons/l10n_es_vat_book_igic/readme/DESCRIPTION.md
odoo/addons/l10n_es_vat_book_igic/readme/INSTALL.md
odoo/addons/l10n_es_vat_book_igic/readme/USAGE.md
odoo/addons/l10n_es_vat_book_igic/static/description/icon.png
odoo/addons/l10n_es_vat_book_igic/static/description/index.html
odoo/addons/l10n_es_vat_book_igic/tests/__init__.py
odoo/addons/l10n_es_vat_book_igic/tests/test_l10n_es_vat_book_igic.py
odoo_addon_l10n_es_vat_book_igic-17.0.1.0.1.dist-info/METADATA
odoo_addon_l10n_es_vat_book_igic-17.0.1.0.1.dist-info/WHEEL
odoo_addon_l10n_es_vat_book_igic-17.0.1.0.1.dist-info/top_level.txt
odoo_addon_l10n_es_vat_book_igic-17.0.1.0.1.dist-info/RECORD
